README.md
setup.py
tempo/__init__.py
tempo/config.py
tempo/worklog.py
tempo_log.egg-info/PKG-INFO
tempo_log.egg-info/SOURCES.txt
tempo_log.egg-info/dependency_links.txt
tempo_log.egg-info/entry_points.txt
tempo_log.egg-info/requires.txt
tempo_log.egg-info/top_level.txt