Metadata-Version: 1.0
Name: tempo-log
Version: 0.0.3
Summary: logging workload from console
Home-page: https://github.com/utek/tlog
Author: Łukasz Bołdys
Author-email: UNKNOWN
License: UNKNOWN
Platform: UNKNOWN
